pponnxcr/__init__.py
pponnxcr/log.py
pponnxcr/predict_system.py
pponnxcr/utility.py
pponnxcr/cls/__init__.py
pponnxcr/cls/postprocess.py
pponnxcr/cls/predict_cls.py
pponnxcr/det/__init__.py
pponnxcr/det/postprocess.py
pponnxcr/det/predict_det.py
pponnxcr/det/preprocess.py
pponnxcr/model/cls.onnx
pponnxcr/model/det.onnx
pponnxcr/model/ppocrv5_dict.txt
pponnxcr/model/rec.onnx
pponnxcr/rec/__init__.py
pponnxcr/rec/predict_rec.py
pponnxcr/rec/rec_decoder.py
pponnxocr-0.1.dist-info/licenses/LICENSE
pponnxocr-0.1.dist-info/METADATA
pponnxocr-0.1.dist-info/WHEEL
pponnxocr-0.1.dist-info/top_level.txt
pponnxocr-0.1.dist-info/RECORD
